{
  "triggers": [
    {
      "id": "Operation_Mode_Trigger",
      "title": {
        "en": "Operation mode has changed to..."
      },
      "titleFormatted": {
        "en": "Operation mode has changed to [[operation_mode_trigger]]"
      },
      "args": [
        {
          "name": "operation_mode_trigger",
          "type": "dropdown",
          "values": [
            {
              "id": "0",
              "label": {
                "en": "Idle"
              }
            },
            {
              "id": "1",
              "label": {
                "en": "Domestic Hot Water"
              }
            },
            {
              "id": "2",
              "label": {
                "en": "Heating"
              }
            },
            {
              "id": "3",
              "label": {
                "en": "Cooling"
              }
            },
            {
              "id": "4",
              "label": {
                "en": "Defrost"
              }
            },
            {
              "id": "5",
              "label": {
                "en": "Standby"
              }
            },
            {
              "id": "6",
              "label": {
                "en": "Legionella"
              }
            }
          ]
        }
      ]
    },
    {
      "id": "Pump1_Thermostat_Trigger",
      "title": {
        "en": "Zone operation mode has changed to..."
      },
      "titleFormatted": {
        "en": "Zone operation mode has changed to [[mode_hpz1_action]]"
      },
      "args": [
        {
          "name": "mode_hpz1_action",
          "type": "dropdown",
          "values": [
            {
              "id": "0",
              "title": {
                "en": "Heat Room"
              }
            },
            {
              "id": "1",
              "title": {
                "en": "Heat Flow"
              }
            },
            {
              "id": "2",
              "title": {
                "en": "Curve"
              }
            },
            {
              "id": "3",
              "title": {
                "en": "Cool Room"
              }
            },
            {
              "id": "4",
              "title": {
                "en": "Cool Flow"
              }
            }
          ]
        }
      ]
    },
    {
      "id": "Forced_Water_Trigger",
      "title": {
        "en": "Forced hot water has changed to..."
      },
      "titleFormatted": {
        "en": "Forced hot water has changed to [[forced_hot_water_trigger]]"
      },
      "args": [
        {
          "name": "forced_hot_water_trigger",
          "type": "dropdown",
          "values": [
            {
              "id": "false",
              "label": {
                "en": "Auto"
              }
            },
            {
              "id": "true",
              "label": {
                "en": "Heat Now"
              }
            }
          ]
        }
      ]
    },
    {
      "id": "Hot_Water_Trigger",
      "title": {
        "en": "Flow temperature has changed"
      },
      "args": []
    },
    {
      "id": "Cold_Water_Trigger",
      "title": {
        "en": "Return temperature has changed"
      },
      "args": []
    }
  ],
  "conditions": [
    {
      "id": "Operation_Mode_Condition",
      "title": {
        "en": "Operation mode !{{equals|doesn't equal}} to..."
      },
      "titleFormatted": {
        "en": "Operation mode !{{equals|doesn't equal}} to [[operation_mode_condition]]"
      },
      "args": [
        {
          "name": "operation_mode_condition",
          "type": "dropdown",
          "values": [
            {
              "id": "0",
              "label": {
                "en": "Idle"
              }
            },
            {
              "id": "1",
              "label": {
                "en": "Domestic Hot Water"
              }
            },
            {
              "id": "2",
              "label": {
                "en": "Heating"
              }
            },
            {
              "id": "3",
              "label": {
                "en": "Cooling"
              }
            },
            {
              "id": "4",
              "label": {
                "en": "Defrost"
              }
            },
            {
              "id": "5",
              "label": {
                "en": "Standby"
              }
            },
            {
              "id": "6",
              "label": {
                "en": "Legionella"
              }
            }
          ]
        }
      ]
    },
    {
      "id": "Pump1_Thermostat_Condition",
      "title": {
        "en": "Zone operation mode !{{equals|doesn't equal}} to..."
      },
      "titleFormatted": {
        "en": "Zone operation mode !{{equals|doesn't equal}} to [[mode_hpz1_condition]]"
      },
      "args": [
        {
          "name": "mode_hpz1_condition",
          "type": "dropdown",
          "values": [
            {
              "id": "0",
              "title": {
                "en": "Heat Room"
              }
            },
            {
              "id": "1",
              "title": {
                "en": "Heat Flow"
              }
            },
            {
              "id": "2",
              "title": {
                "en": "Curve"
              }
            },
            {
              "id": "3",
              "title": {
                "en": "Cool Room"
              }
            },
            {
              "id": "4",
              "title": {
                "en": "Cool Flow"
              }
            }
          ]
        }
      ]
    },
    {
      "id": "Forced_Hot_Water_Condition",
      "title": {
        "en": "Forced hot water !{{equals|doesn't equal}} to..."
      },
      "titleFormatted": {
        "en": "Forced hot water !{{equals|doesn't equal}} to [[forced_hot_water_condition]]"
      },
      "args": [
        {
          "name": "forced_hot_water_condition",
          "type": "dropdown",
          "values": [
            {
              "id": "false",
              "label": {
                "en": "Auto"
              }
            },
            {
              "id": "true",
              "label": {
                "en": "Heat Now"
              }
            }
          ]
        }
      ]
    },
    {
      "id": "Cold_Water_Condition",
      "title": {
        "en": "Flow temperature !{{is|isn't}} lower than..."
      },
      "titleFormatted": {
        "en": "Flow temperature !{{is|isn't}} lower than [[cold_water_value]]"
      },
      "args": [
        {
          "name": "cold_water_value",
          "type": "number",
          "min": 10,
          "max": 60,
          "placeholder": {
            "en": "value"
          }
        }
      ]
    },
    {
      "id": "Hot_Water_Condition",
      "title": {
        "en": "Return temperature !{{is|isn't}} greater than..."
      },
      "titleFormatted": {
        "en": "Return temperature !{{is|isn't}} greater than [[hot_water_value]]"
      },
      "args": [
        {
          "name": "hot_water_value",
          "type": "number",
          "min": 10,
          "max": 60,
          "placeholder": {
            "en": "value"
          }
        }
      ]
    },
    {
      "id": "alarm_DefrostMode_Condition",
      "title": {
        "en": "Defrost Mode !{{is|isn't}} On"
      },
      "args": []
    },
    {
      "id": "alarm_BoosterHeater1_Condition",
      "title": {
        "en": "Booster Heater 1 !{{is|isn't}} On"
      },
      "args": []
    },
    {
      "id": "alarm_BoosterHeater2_Condition",
      "title": {
        "en": "Booster Heater 2 !{{is|isn't}} On"
      },
      "args": []
    },
    {
      "id": "alarm_BoosterHeater2Plus_Condition",
      "title": {
        "en": "Booster Heater 2 Plus !{{is|isn't}} On"
      },
      "args": []
    },
    {
      "id": "alarm_ImmersionHeater_Condition",
      "title": {
        "en": "Immersion Heater !{{is|isn't}} On"
      },
      "args": []
    }
  ],
  "actions": [
    {
      "id": "Pump1_Thermostat_Action",
      "title": {
        "en": "Set zone operation mode to..."
      },
      "titleFormatted": {
        "en": "Set zone operation mode to [[mode_hpom_action]]"
      },
      "args": [
        {
          "name": "mode_hpom_action",
          "type": "dropdown",
          "values": [
            {
              "id": "0",
              "title": {
                "en": "Heat Room"
              }
            },
            {
              "id": "1",
              "title": {
                "en": "Heat Flow"
              }
            },
            {
              "id": "2",
              "title": {
                "en": "Curve"
              }
            },
            {
              "id": "3",
              "title": {
                "en": "Cool Room"
              }
            },
            {
              "id": "4",
              "title": {
                "en": "Cool Flow"
              }
            }
          ]
        }
      ]
    },
    {
      "id": "Forced_Hot_Water_Action",
      "title": {
        "en": "Set forced hot water to..."
      },
      "titleFormatted": {
        "en": "Set forced hot water to [[forced_hot_water_action]]"
      },
      "args": [
        {
          "name": "forced_hot_water_action",
          "type": "dropdown",
          "values": [
            {
              "id": "false",
              "label": {
                "en": "Auto"
              }
            },
            {
              "id": "true",
              "label": {
                "en": "Heat Now"
              }
            }
          ]
        }
      ]
    },
    {
      "id": "Heat_Water_Action",
      "title": {
        "en": "Set heat flow temperature..."
      },
      "titleFormatted": {
        "en": "Set heat flow temperature to [[heat_water_value]]"
      },
      "args": [
        {
          "name": "heat_water_value",
          "type": "number",
          "min": 10,
          "max": 60,
          "placeholder": {
            "en": "value"
          }
        }
      ]
    },
    {
      "id": "Cool_Water_Action",
      "title": {
        "en": "Set cool flow temperature to..."
      },
      "titleFormatted": {
        "en": "Set cool flow temperature to [[cool_water_value]]"
      },
      "args": [
        {
          "name": "cool_water_value",
          "type": "number",
          "min": 10,
          "max": 60,
          "placeholder": {
            "en": "value"
          }
        }
      ]
    },
    {
      "id": "Water_Tank_Temp_Action",
      "title": {
        "en": "Set water tank temperature to..."
      },
      "titleFormatted": {
        "en": "Set water tank temperature to [[tank_water_value]]"
      },
      "args": [
        {
          "name": "tank_water_value",
          "type": "number",
          "min": 40,
          "max": 60,
          "placeholder": {
            "en": "value"
          }
        }
      ]
    }
  ]
}